Metadata-Version: 1.1
Name: sintxcs
Version: 0.0.1
Summary: Sintacs Collection of Made Modules
Home-page: UNKNOWN
Author: Sintacs
Author-email: sintacs@isnotdev.com
License: MIT
Keywords: Sintxcs
Platform: UNKNOWN
Classifier: Development Status :: 5 - Production/Stable
Classifier: Intended Audience :: Education
Classifier: Operating System :: Microsoft :: Windows :: Windows 10
Classifier: License :: OSI Approved :: MIT License
Classifier: Programming Language :: Python :: 3
